barcode_decoder/__init__.py
barcode_decoder/app.py
barcode_decoder/barcode_decoder.py
barcode_decoder/digi_key.py
barcode_decoder/farnell.py
barcode_decoder/mouser.py
barcode_decoder/result.py
barcode_decoder/scanner.py
barcode_decoder/tme.py
barcode_decoder/wurth_elektronik.py
barcode_decoder-0.1.5.dist-info/LICENSE
barcode_decoder-0.1.5.dist-info/METADATA
barcode_decoder-0.1.5.dist-info/WHEEL
barcode_decoder-0.1.5.dist-info/entry_points.txt
barcode_decoder-0.1.5.dist-info/top_level.txt
barcode_decoder-0.1.5.dist-info/RECORD
