Metadata-Version: 2.2
Name: barcode_decoder
Version: 0.1.5
Summary: Library to convert electronic components distributors  barcodes and QR codes to unified format. Library allows to extract information about: partnumber, ordered quantity, order number, part LOT and origin.
Home-page: https://github.com/partmanager/barcode-decoder
Author: sakoPO
Project-URL: Bug Tracker, https://github.com/partmanager/barcode-decoder/issues
Project-URL: Changelog, https://github.com/partmanager/barcode-decoder/releases
Project-URL: Source Code, https://github.com/partmanager/barcode-decoder
Project-URL: Documentation, https://partmanager.github.io/barcode-decoder
Classifier: Programming Language :: Python :: 3
Classifier: Intended Audience :: Developers
Classifier: Intended Audience :: Manufacturing
Classifier: License :: OSI Approved :: GNU General Public License v3 (GPLv3)
Classifier: Operating System :: OS Independent
Requires-Python: >=3.9
License-File: LICENSE
